{"Vista_Rapida": [["20Minutos.Es", "www.20minutos.es"], ["Abc", "www.abc.es"], ["Alerta_Digital", "www.alertadigital.com"], ["China.Org", "spanish.china.org.cn"], ["Eldiario.Es", "www.eldiario.es"], ["El_Confidencial", "www.elconfidencial.com"], ["El_Economista", "www.eleconomista.es"], ["El_Huffington_Post", "www.huffingtonpost.es"], ["El_Mundo", "www.elmundo.es"], ["El_Mundo_Today", "www.elmundotoday.com"], ["El_Pais", "elpais.com"], ["La_Haine", "www.lahaine.org"], ["La_Vanguardia", "www.lavanguardia.com"], ["Libertad_Digital", "www.libertaddigital.com"], ["Publico", "www.publico.es"], ["Rt_Sepa_Mas", "actualidad.rt.com"], ["Rebelion.Org", "rebelion.org"], ["Sputnik_Mundo", "mundo.sputniknews.com"]], "Prensa_Economica": [["Bolsamania", "www.bolsamania.com"], ["Burbuja_Economica", "www.burbuja.info"], ["Capital_Madrid", "www.capitalmadrid.com"], ["Cnn_Expansion", "expansion.mx"], ["Diario_Abierto", "www.diarioabierto.es"], ["Diario_Negocio", "www.neg-ocio.com"], ["Economia_Digital", "www.economiadigital.es"], ["El_Blog_Salmon", "www.elblogsalmon.com"], ["El_Economista", "www.eleconomista.es"], ["El_Referente", "elreferente.es"], ["Estrategias_De_Inversion", "www.estrategiasdeinversion.com"], ["Expansion", "www.expansion.com"], ["Financial_Red", "financialred.com"], ["Forbes_Mexico", "www.forbes.com.mx"], ["Funds_People", "es.fundspeople.com"], ["La_Carta_De_La_Bolsa", "lacartadelabolsa.com"], ["Libre_Mercado", "www.libremercado.com"], ["Megabolsa", "www.megabolsa.com"], ["Mercaamerica", "mercamerica.es"], ["Oro_Y_Finanzas", "www.oroyfinanzas.com"], ["Tu_Capital", "www.tucapital.es"]], "La_Otra_Informacion_Que_No_Te_Cuentan": [["Acratas.Net", "acratasnet.wordpress.com"], ["Aporrea", "www.aporrea.org"], ["Canarias-Semanal.Org", "canarias-semanal.org"], ["Democracy_Now!", "www.democracynow.org"], ["Diario_De_Octubre", "diario-octubre.com"], ["Eco_Republicano", "www.ecorepublicano.es"], ["El_Comunista", "elcomunista.net"], ["El_Espia_Digital", "elespiadigital.com"], ["El_Salto", "www.elsaltodiario.com"], ["Espia_En_El_Congreso", "espiaenelcongreso.com"], ["Iniciativa_Debate", "iniciativadebate.org"], ["Insurgente.Org", "insurgente.org"], ["Kaosenlared.Net", "kaosenlared.net"], ["La_Haine", "www.lahaine.org"], ["La_Republica", "larepublica.es"], ["La_Tercera_Informacion", "www.tercerainformacion.es"], ["Libre_Red", "www.librered.net"], ["La_Marea", "www.lamarea.com"], ["Nodo50.Org", "info.nodo50.org"], ["Rebelion.Org", "rebelion.org"], ["Red_Voltaire", "www.voltairenet.org"], ["Sin_Permiso", "www.sinpermiso.info"]], "Televisiones_Y_Radios_Informativos": [["Antena_3_Noticias", "www.antena3.com"], ["Bbc", "www.bbc.com"], ["Cadena_Ser", "cadenaser.com"], ["Cope", "www.cope.es"], ["Cuatro", "www.cuatro.com"], ["Cnn", "cnnespanol.cnn.com"], ["Euronews", "es.euronews.com"], ["Hispantv", "www.hispantv.com"], ["Informativos_Tele-5", "www.telecinco.es"], ["Intereconomia", "www.intereconomia.com"], ["Onda_Cero", "www.ondacero.es"], ["Radio_Television_Espanola", "www.rtve.es"], ["La_Sexta", "www.lasexta.com"], ["Radio_Francia", "www.rfi.fr"], ["Rusia_Today", "actualidad.rt.com"], ["Tele_Sur", "www.telesurtv.net"]], "Asociaciones": [["Adicae", "www.adicae.net"], ["Auc", "www.auc.es"], ["Aui.Es", "www.aui.es"], ["Cecu", "cecu.es"], ["Facua.Org", "www.facua.org"], ["Internautas.Org", "www.internautas.org"], ["Ocu", "www.ocu.org"]], "Prensa_General": [["Alerta_Digital", "www.alertadigital.com"], ["Alnavio", "alnavio.com"], ["Ctxt-Revista_Contexto", "ctxt.es"], ["De_Verdad_Digital", "deverdaddigital.com"], ["Diario_16", "diario16.com"], ["Diario_Critico", "www.diariocritico.com"], ["Dignidad_Digital", "www.dignidaddigital.com"], ["Diario_Republica_Constitucional", "www.diariorc.com"], ["Eldiario.Es", "www.eldiario.es"], ["El_Boletin", "www.elboletin.com"], ["El_Cierre_Digital", "elcierredigital.com"], ["El_Confidencial_Digital", "www.elconfidencialdigital.com"], ["El_Cuarto_Poder", "www.cuartopoder.es"], ["El_Espanol", "www.elespanol.com"], ["El_Imparcial", "www.elimparcial.es"], ["El_Independiente", "www.elindependiente.com"], ["El_Periodico", "www.elperiodico.com"], ["El_Plural", "www.elplural.com"], ["El_Semanal_Digital", "www.esdiario.com"], ["Esdiario", "www.esdiario.com"], ["Espana_Diario", "diarioespana.com"], ["Euro_Mundo_Global", "www.euromundoglobal.com"], ["Extraconfidencial", "extraconfidencial.com"], ["Gente_Digital", "www.gentedigital.es"], ["Hechos_De_Hoy", "www.hechosdehoy.com"], ["Hispanidad", "www.hispanidad.com"], ["Iblnews", "iblnews.org"], ["Infolibre", "www.infolibre.es"], ["La_Estrella_Digital", "www.estrelladigital.es"], ["La_Hora_Digital", "lahoradigital.com"], ["La_Informacion", "www.lainformacion.com"], ["La_Marea", "www.lamarea.com"], ["La_Razon", "www.larazon.es"], ["La_Voz_Libre", "vozlibre.com"], ["Libertad_Digital", "www.libertaddigital.com"], ["Naiz", "www.naiz.eus"], ["Nuevatribuna", "www.nuevatribuna.es"], ["Minuto_Digital", "accounts.google.com"], ["Moncloa.Com", "www.moncloa.com"], ["Mundiario", "www.mundiario.com"], ["Okdiario", "okdiario.com"], ["Periodista_Digital", "www.periodistadigital.com"], ["Postdigital", "postdigital.es"], ["Que", "www.que.es"], ["Republica", "www.republica.com"], ["Siglo_Xxi", "www.diariosigloxxi.com"], ["Son_Buenas_Noticias", "www.sonbuenasnoticias.com"], ["Tribuna_Forum", "tribunaforum.es"], ["Vozpopuli", "www.vozpopuli.com"]], "Prensa_Deportiva": [["Acb", "www.acb.com"], ["As", "as.com"], ["Diario_Gol", "www.diariogol.com"], ["Eldesmarque", "eldesmarque.com"], ["Espn__Deportes", "espndeportes.espn.com"], ["Estadio_Deportivo", "www.estadiodeportivo.com"], ["Eurosport", "www.eurosport.es"], ["Futbol_En_La_Tv", "www.futbolenlatv.es"], ["Laotraliga.Net", "laotraliga.net"], ["Marca", "www.marca.com"], ["Moto_Gp", "www.motogp.com"], ["Motorciclismo", "www.motociclismo.es"], ["Mundo_Deportivo", "www.mundodeportivo.com"], ["Nba", "es.nba.com"], ["Rincon_Del_Motor", "rincondelmotor.com"], ["Sport", "www.sport.es"], ["Super_Deporte", "www.superdeporte.es"], ["Ten_Golf", "ten-golf.com"]], "Agencias_De_Noticias": [["Abi", "www2.abi.bo"], ["Agencia_Ansa", "www.ansalatina.com"], ["Agencia_Efe", "www.efe.com"], ["Alainet", "www.alainet.org"], ["Andes", "www.redaktionstest.net"], ["Avn", "www.avn.info.ve"], ["Boletin_Oficial_Del_Estado_-_Espana", "www.boe.es"], ["Europa_Press", "www.europapress.es"], ["Ips_Noticias", "www.ipsnoticias.net"], ["Nomitex", "www.notimex.com.mx"], ["Prensa_Latina", "www.prensa-latina.cu"], ["Reuters", "es.reuters.com"], ["Rianovosti", "mundo.sputniknews.com"], ["Telam", "www.telam.com.ar"], ["United_Press_International", "espanol.upi.com"]], "Tecnologia_De_La_Informacion": [["Applesfera", "www.applesfera.com"], ["Baquia.Com", "www.baquia.com"], ["Denken_Uber", "www.uberbin.net"], ["El_Blog_De_Enrique_Dans", "www.enriquedans.com"], ["Error500", "www.error500.net"], ["Fayerwayer", "www.fayerwayer.com"], ["Geek`S_Room", "geeksroom.com"], ["Hipertextual", "hipertextual.com"], ["Genbeta", "www.genbeta.com"], ["Idg", "www.idg.es"], ["Itespresso", "www.itespresso.es"], ["La_Flecha", "laflecha.net"], ["Marc_Vidal", "www.marcvidal.net"], ["Navegante", "www.elmundo.es"], ["Puro_Marketing", "www.puromarketing.com"], ["Red.Es", "www.red.es"], ["Siliconnews", "siliconnews.plataformasinc.es"], ["Ticbeat", "www.ticbeat.com"], ["Wwwhat'S_News", "wwwhatsnew.com"], ["Xacata", "www.xataka.com"], ["Zona_Virus", "www.zonavirus.com"]], "Religion": [["Aciprensa", "www.aciprensa.com"], ["Infocatolica", "www.infocatolica.com"], ["Redes_Cristianas", "www.redescristianas.net"], ["Religion_Digital", "www.religiondigital.org"], ["Web_Islam", "www.verislam.com"]]}